aoirint_psdlayer2dirpy/__init__.py
aoirint_psdlayer2dirpy/main.py
aoirint_psdlayer2dirpy-20220819.3.dist-info/LICENSE
aoirint_psdlayer2dirpy-20220819.3.dist-info/METADATA
aoirint_psdlayer2dirpy-20220819.3.dist-info/WHEEL
aoirint_psdlayer2dirpy-20220819.3.dist-info/entry_points.txt
aoirint_psdlayer2dirpy-20220819.3.dist-info/top_level.txt
aoirint_psdlayer2dirpy-20220819.3.dist-info/RECORD
