Metadata-Version: 2.1
Name: aoirint-psdlayer2dirpy
Version: 20220819.3
Summary: PSDファイルのレイヤー構造＋画像をディレクトリ構造＋PNGとしてダンプするスクリプト
Home-page: https://github.com/aoirint/psdlayer2dirpy
Author: aoirint
Author-email: aoirint@gmail.com
Classifier: Development Status :: 3 - Alpha
Classifier: Programming Language :: Python
Classifier: Programming Language :: Python :: 3
Classifier: Programming Language :: Python :: 3.9
License-File: LICENSE
Requires-Dist: psd-tools
